Workbook
Name Barranquilla: Formato!$J$61:$J$63
Name BCEMPRESARIAL: Formato!$N$61:$N$64
Name PLANTA1: Formato!$N$61:$N$64
Name PLANTA2: Formato!$N$65:$N$67
Name PLANTA3: Formato!$N$79:$N$80
Name PLANTA4: Formato!$N$68:$N$78

Sheet Formato
E2: FORMATO DE REQUISICIÓN Y DEVOLUCIÓN DE MATERIALES | P2: VERSIÓN: 52
P6: PÁGINA: 1 de 1
B11: Ciudad Origen Movimiento | E11: Villavicencio | Y11: Doc. Referencia
B14: Clase de movimiento | K14: Fecha de Solicitud | L14: 46294
L15: 3
K16: Consecutivo | M16: 1 | AG16: ZZ.CO11.250130.31
P17: Usar solo en caso de traslado | W17: Solo en caso de proyectos | AG17: observacionZZ.CO11.250130.31
A18: COD RESERVA | B18: Código artículo | C18: Cantidad | D18: Und | E18: Descripción | M18: Planta de Origen | N18: Storage Location Origen | O18: No de Serial | P18: Planta de Destino | V18: Storage Location Destino | W18: No WBS/Proyecto | AF18: Entrada | AG18: OBSERVACION | AJ18: Planta | AK18: Opcion
D19: =IF(ISERROR(VLOOKUP(B19,$A$61:$C$30467,3,FALSE))=TRUE," ",VLOOKUP(B19,$A$61:$C$30467,3,FALSE)) | E19: =IF(ISERROR(VLOOKUP(B19,$A$61:$C$30000,2,FALSE))=TRUE," ",VLOOKUP(B19,$A$61:$C$30000,2,FALSE)) | M19: CO29 LN Villavicencio | Z19: {=_xlfn._xlws.FILTER(TablaOpciones[Opcion],TablaOpciones[Planta]=P19,0)} -> 0 | AA19: {=_xlfn._xlws.FILTER(TablaOpciones[Opcion],TablaOpciones[Planta]=$M$19,0)} -> ALMAGRARIO | AD19: Barranquilla | AE19: {=_xlfn.UNIQUE(TablaOpciones[Planta],FALSE,FALSE)} -> CO01 LN-BC Empresarial | AF19: Traslado | AH19: {=IF(B19="","",IF(SUMPRODUCT((Hoja2!$A$2:$A$121&""=B19&"")*(TRIM(Hoja2!$F$2:$F$121)=TRIM(N19))*(TRIM(Hoja2!$L$2:$L$121)=TRIM(W19)))>0,SUMPRODUCT((Hoja2!$A$2:$A$121&""=B19&"")*(TRIM(Hoja2!$F$2:$F$121)=TRIM(N19))*(TRIM(Hoja2!$L$2:$L$121)=TRIM(W19))*Hoja2!$I$2:$I$121),SUMPRODUCT((Hoja2!$A$2:$A$121&""=B19&"")*(TRIM(Hoja2!$F$2:$F$121)=TRIM(N19))*(Hoja2!$L$2:$L$121="")*Hoja2!$I$2:$I$121)))} | AJ19: CO01 LN-BC Empresarial | AK19: PROMITEL
D20: =IF(ISERROR(VLOOKUP(B20,$A$61:$C$30467,3,FALSE))=TRUE," ",VLOOKUP(B20,$A$61:$C$30467,3,FALSE)) | E20: =IF(ISERROR(VLOOKUP(B20,$A$61:$C$30000,2,FALSE))=TRUE," ",VLOOKUP(B20,$A$61:$C$30000,2,FALSE)) | M20: CO29 LN Villavicencio | AA20: NODO | AD20: Puerto Colombia | AE20: CO02 LN-Steckerl | AH20: {=IF(B20="","",IF(SUMPRODUCT((Hoja2!$A$2:$A$121&""=B20&"")*(TRIM(Hoja2!$F$2:$F$121)=TRIM(N20))*(TRIM(Hoja2!$L$2:$L$121)=TRIM(W20)))>0,SUMPRODUCT((Hoja2!$A$2:$A$121&""=B20&"")*(TRIM(Hoja2!$F$2:$F$121)=TRIM(N20))*(TRIM(Hoja2!$L$2:$L$121)=TRIM(W20))*Hoja2!$I$2:$I$121),SUMPRODUCT((Hoja2!$A$2:$A$121&""=B20&"")*(TRIM(Hoja2!$F$2:$F$121)=TRIM(N20))*(Hoja2!$L$2:$L$121="")*Hoja2!$I$2:$I$121)))} | AJ20: CO01 LN-BC Empresarial | AK20: WOM
D21: =IF(ISERROR(VLOOKUP(B21,$A$61:$C$30467,3,FALSE))=TRUE," ",VLOOKUP(B21,$A$61:$C$30467,3,FALSE)) | E21: =IF(ISERROR(VLOOKUP(B21,$A$61:$C$30000,2,FALSE))=TRUE," ",VLOOKUP(B21,$A$61:$C$30000,2,FALSE)) | M21: CO29 LN Villavicencio | AA21: WOM | AD21: Cartagena | AE21: CO04 LN-Bogota | AH21: {=IF(B21="","",IF(SUMPRODUCT((Hoja2!$A$2:$A$121&""=B21&"")*(TRIM(Hoja2!$F$2:$F$121)=TRIM(N21))*(TRIM(Hoja2!$L$2:$L$121)=TRIM(W21)))>0,SUMPRODUCT((Hoja2!$A$2:$A$121&""=B21&"")*(TRIM(Hoja2!$F$2:$F$121)=TRIM(N21))*(TRIM(Hoja2!$L$2:$L$121)=TRIM(W21))*Hoja2!$I$2:$I$121),SUMPRODUCT((Hoja2!$A$2:$A$121&""=B21&"")*(TRIM(Hoja2!$F$2:$F$121)=TRIM(N21))*(Hoja2!$L$2:$L$121="")*Hoja2!$I$2:$I$121)))} | AJ21: CO02 LN-Steckerl | AK21: STECKERL
D22: =IF(ISERROR(VLOOKUP(B22,$A$61:$C$30467,3,FALSE))=TRUE," ",VLOOKUP(B22,$A$61:$C$30467,3,FALSE)) | E22: =IF(ISERROR(VLOOKUP(B22,$A$61:$C$30000,2,FALSE))=TRUE," ",VLOOKUP(B22,$A$61:$C$30000,2,FALSE)) | M22: CO29 LN Villavicencio | AD22: Cali | AE22: CO03 LN-Bodega Nogales | AH22: {=IF(B22="","",IF(SUMPRODUCT((Hoja2!$A$2:$A$121&""=B22&"")*(TRIM(Hoja2!$F$2:$F$121)=TRIM(N22))*(TRIM(Hoja2!$L$2:$L$121)=TRIM(W22)))>0,SUMPRODUCT((Hoja2!$A$2:$A$121&""=B22&"")*(TRIM(Hoja2!$F$2:$F$121)=TRIM(N22))*(TRIM(Hoja2!$L$2:$L$121)=TRIM(W22))*Hoja2!$I$2:$I$121),SUMPRODUCT((Hoja2!$A$2:$A$121&""=B22&"")*(TRIM(Hoja2!$F$2:$F$121)=TRIM(N22))*(Hoja2!$L$2:$L$121="")*Hoja2!$I$2:$I$121)))} | AJ22: CO04 LN-Bogota | AK22: LN Bogota
D23: =IF(ISERROR(VLOOKUP(B23,$A$61:$C$30467,3,FALSE))=TRUE," ",VLOOKUP(B23,$A$61:$C$30467,3,FALSE)) | E23: =IF(ISERROR(VLOOKUP(B23,$A$61:$C$30000,2,FALSE))=TRUE," ",VLOOKUP(B23,$A$61:$C$30000,2,FALSE)) | M23: CO29 LN Villavicencio | AD23: Bucaramanga | AE23: CO05 LN-Cabecera Bucaramanga | AH23: {=IF(B23="","",IF(SUMPRODUCT((Hoja2!$A$2:$A$121&""=B23&"")*(TRIM(Hoja2!$F$2:$F$121)=TRIM(N23))*(TRIM(Hoja2!$L$2:$L$121)=TRIM(W23)))>0,SUMPRODUCT((Hoja2!$A$2:$A$121&""=B23&"")*(TRIM(Hoja2!$F$2:$F$121)=TRIM(N23))*(TRIM(Hoja2!$L$2:$L$121)=TRIM(W23))*Hoja2!$I$2:$I$121),SUMPRODUCT((Hoja2!$A$2:$A$121&""=B23&"")*(TRIM(Hoja2!$F$2:$F$121)=TRIM(N23))*(Hoja2!$L$2:$L$121="")*Hoja2!$I$2:$I$121)))} | AJ23: CO04 LN-Bogota | AK23: WOM
D24: =IF(ISERROR(VLOOKUP(B24,$A$61:$C$30467,3,FALSE))=TRUE," ",VLOOKUP(B24,$A$61:$C$30467,3,FALSE)) | E24: =IF(ISERROR(VLOOKUP(B24,$A$61:$C$30000,2,FALSE))=TRUE," ",VLOOKUP(B24,$A$61:$C$30000,2,FALSE)) | M24: CO29 LN Villavicencio | AD24: Santa Marta | AE24: CO06 LN-Almagrario Bucaramanga | AH24: {=IF(B24="","",IF(SUMPRODUCT((Hoja2!$A$2:$A$121&""=B24&"")*(TRIM(Hoja2!$F$2:$F$121)=TRIM(N24))*(TRIM(Hoja2!$L$2:$L$121)=TRIM(W24)))>0,SUMPRODUCT((Hoja2!$A$2:$A$121&""=B24&"")*(TRIM(Hoja2!$F$2:$F$121)=TRIM(N24))*(TRIM(Hoja2!$L$2:$L$121)=TRIM(W24))*Hoja2!$I$2:$I$121),SUMPRODUCT((Hoja2!$A$2:$A$121&""=B24&"")*(TRIM(Hoja2!$F$2:$F$121)=TRIM(N24))*(Hoja2!$L$2:$L$121="")*Hoja2!$I$2:$I$121)))} | AJ24: CO04 LN-Bogota | AK24: CN-COLBOG
D25: =IF(ISERROR(VLOOKUP(B25,$A$61:$C$30467,3,FALSE))=TRUE," ",VLOOKUP(B25,$A$61:$C$30467,3,FALSE)) | E25: =IF(ISERROR(VLOOKUP(B25,$A$61:$C$30000,2,FALSE))=TRUE," ",VLOOKUP(B25,$A$61:$C$30000,2,FALSE)) | M25: CO29 LN Villavicencio | AD25: Sincelejo | AE25: CO07 LN-Piedecuesta Bucaramanga | AH25: {=IF(B25="","",IF(SUMPRODUCT((Hoja2!$A$2:$A$121&""=B25&"")*(TRIM(Hoja2!$F$2:$F$121)=TRIM(N25))*(TRIM(Hoja2!$L$2:$L$121)=TRIM(W25)))>0,SUMPRODUCT((Hoja2!$A$2:$A$121&""=B25&"")*(TRIM(Hoja2!$F$2:$F$121)=TRIM(N25))*(TRIM(Hoja2!$L$2:$L$121)=TRIM(W25))*Hoja2!$I$2:$I$121),SUMPRODUCT((Hoja2!$A$2:$A$121&""=B25&"")*(TRIM(Hoja2!$F$2:$F$121)=TRIM(N25))*(Hoja2!$L$2:$L$121="")*Hoja2!$I$2:$I$121)))} | AJ25: CO04 LN-Bogota | AK25: CN-PMBOG
D26: =IF(ISERROR(VLOOKUP(B26,$A$61:$C$30467,3,FALSE))=TRUE," ",VLOOKUP(B26,$A$61:$C$30467,3,FALSE)) | E26: =IF(ISERROR(VLOOKUP(B26,$A$61:$C$30000,2,FALSE))=TRUE," ",VLOOKUP(B26,$A$61:$C$30000,2,FALSE)) | M26: CO29 LN Villavicencio | AD26: Monteria | AE26: CO08 LN-Santa Monica Cali | AH26: {=IF(B26="","",IF(SUMPRODUCT((Hoja2!$A$2:$A$121&""=B26&"")*(TRIM(Hoja2!$F$2:$F$121)=TRIM(N26))*(TRIM(Hoja2!$L$2:$L$121)=TRIM(W26)))>0,SUMPRODUCT((Hoja2!$A$2:$A$121&""=B26&"")*(TRIM(Hoja2!$F$2:$F$121)=TRIM(N26))*(TRIM(Hoja2!$L$2:$L$121)=TRIM(W26))*Hoja2!$I$2:$I$121),SUMPRODUCT((Hoja2!$A$2:$A$121&""=B26&"")*(TRIM(Hoja2!$F$2:$F$121)=TRIM(N26))*(Hoja2!$L$2:$L$121="")*Hoja2!$I$2:$I$121)))} | AJ26: CO04 LN-Bogota | AK26: COLCSC NEW
D27: =IF(ISERROR(VLOOKUP(B27,$A$61:$C$30467,3,FALSE))=TRUE," ",VLOOKUP(B27,$A$61:$C$30467,3,FALSE)) | E27: =IF(ISERROR(VLOOKUP(B27,$A$61:$C$30000,2,FALSE))=TRUE," ",VLOOKUP(B27,$A$61:$C$30000,2,FALSE)) | M27: CO29 LN Villavicencio | Z27: {=_xlfn._xlws.FILTER(TablaOpciones[Opcion],TablaOpciones[Planta]=P20,0)} -> 0 | AA27: {=_xlfn._xlws.FILTER(TablaOpciones[Opcion],TablaOpciones[Planta]=M20,0)} -> ALMAGRARIO | AD27: Popayan | AE27: CO09 LN-Almagrario Cali | AH27: {=IF(B27="","",IF(SUMPRODUCT((Hoja2!$A$2:$A$121&""=B27&"")*(TRIM(Hoja2!$F$2:$F$121)=TRIM(N27))*(TRIM(Hoja2!$L$2:$L$121)=TRIM(W27)))>0,SUMPRODUCT((Hoja2!$A$2:$A$121&""=B27&"")*(TRIM(Hoja2!$F$2:$F$121)=TRIM(N27))*(TRIM(Hoja2!$L$2:$L$121)=TRIM(W27))*Hoja2!$I$2:$I$121),SUMPRODUCT((Hoja2!$A$2:$A$121&""=B27&"")*(TRIM(Hoja2!$F$2:$F$121)=TRIM(N27))*(Hoja2!$L$2:$L$121="")*Hoja2!$I$2:$I$121)))} | AJ27: CO04 LN-Bogota | AK27: CLCSC USED
D28: =IF(ISERROR(VLOOKUP(B28,$A$61:$C$30467,3,FALSE))=TRUE," ",VLOOKUP(B28,$A$61:$C$30467,3,FALSE)) | E28: =IF(ISERROR(VLOOKUP(B28,$A$61:$C$30000,2,FALSE))=TRUE," ",VLOOKUP(B28,$A$61:$C$30000,2,FALSE)) | M28: CO29 LN Villavicencio | AA28: NODO | AD28: Valledupar | AE28: CO10 LN-Almaviva Cartagena | AH28: {=IF(B28="","",IF(SUMPRODUCT((Hoja2!$A$2:$A$121&""=B28&"")*(TRIM(Hoja2!$F$2:$F$121)=TRIM(N28))*(TRIM(Hoja2!$L$2:$L$121)=TRIM(W28)))>0,SUMPRODUCT((Hoja2!$A$2:$A$121&""=B28&"")*(TRIM(Hoja2!$F$2:$F$121)=TRIM(N28))*(TRIM(Hoja2!$L$2:$L$121)=TRIM(W28))*Hoja2!$I$2:$I$121),SUMPRODUCT((Hoja2!$A$2:$A$121&""=B28&"")*(TRIM(Hoja2!$F$2:$F$121)=TRIM(N28))*(Hoja2!$L$2:$L$121="")*Hoja2!$I$2:$I$121)))} | AJ28: CO04 LN-Bogota | AK28: DATACENTER
D29: =IF(ISERROR(VLOOKUP(B29,$A$61:$C$30467,3,FALSE))=TRUE," ",VLOOKUP(B29,$A$61:$C$30467,3,FALSE)) | E29: =IF(ISERROR(VLOOKUP(B29,$A$61:$C$30000,2,FALSE))=TRUE," ",VLOOKUP(B29,$A$61:$C$30000,2,FALSE)) | AA29: WOM | AD29: Bogota | AE29: CO11 LN-Bazurto Cartagena | AH29: {=IF(B29="","",IF(SUMPRODUCT((Hoja2!$A$2:$A$121&""=B29&"")*(TRIM(Hoja2!$F$2:$F$121)=TRIM(N29))*(TRIM(Hoja2!$L$2:$L$121)=TRIM(W29)))>0,SUMPRODUCT((Hoja2!$A$2:$A$121&""=B29&"")*(TRIM(Hoja2!$F$2:$F$121)=TRIM(N29))*(TRIM(Hoja2!$L$2:$L$121)=TRIM(W29))*Hoja2!$I$2:$I$121),SUMPRODUCT((Hoja2!$A$2:$A$121&""=B29&"")*(TRIM(Hoja2!$F$2:$F$121)=TRIM(N29))*(Hoja2!$L$2:$L$121="")*Hoja2!$I$2:$I$121)))} | AJ29: CO04 LN-Bogota | AK29: CFX
D30: =IF(ISERROR(VLOOKUP(B30,$A$61:$C$30467,3,FALSE))=TRUE," ",VLOOKUP(B30,$A$61:$C$30467,3,FALSE)) | E30: =IF(ISERROR(VLOOKUP(B30,$A$61:$C$30000,2,FALSE))=TRUE," ",VLOOKUP(B30,$A$61:$C$30000,2,FALSE)) | AD30: Cucuta | AE30: CO12 LN-CFX Cartagena | AH30: {=IF(B30="","",IF(SUMPRODUCT((Hoja2!$A$2:$A$121&""=B30&"")*(TRIM(Hoja2!$F$2:$F$121)=TRIM(N30))*(TRIM(Hoja2!$L$2:$L$121)=TRIM(W30)))>0,SUMPRODUCT((Hoja2!$A$2:$A$121&""=B30&"")*(TRIM(Hoja2!$F$2:$F$121)=TRIM(N30))*(TRIM(Hoja2!$L$2:$L$121)=TRIM(W30))*Hoja2!$I$2:$I$121),SUMPRODUCT((Hoja2!$A$2:$A$121&""=B30&"")*(TRIM(Hoja2!$F$2:$F$121)=TRIM(N30))*(Hoja2!$L$2:$L$121="")*Hoja2!$I$2:$I$121)))} | AJ30: CO03 LN-Bodega Nogales | AK30: BAJA ROTACION
D31: =IF(ISERROR(VLOOKUP(B31,$A$61:$C$30467,3,FALSE))=TRUE," ",VLOOKUP(B31,$A$61:$C$30467,3,FALSE)) | E31: =IF(ISERROR(VLOOKUP(B31,$A$61:$C$30000,2,FALSE))=TRUE," ",VLOOKUP(B31,$A$61:$C$30000,2,FALSE)) | AD31: Ibague | AE31: CO13 LN-Cucuta | AH31: {=IF(B31="","",IF(SUMPRODUCT((Hoja2!$A$2:$A$121&""=B31&"")*(TRIM(Hoja2!$F$2:$F$121)=TRIM(N31))*(TRIM(Hoja2!$L$2:$L$121)=TRIM(W31)))>0,SUMPRODUCT((Hoja2!$A$2:$A$121&""=B31&"")*(TRIM(Hoja2!$F$2:$F$121)=TRIM(N31))*(TRIM(Hoja2!$L$2:$L$121)=TRIM(W31))*Hoja2!$I$2:$I$121),SUMPRODUCT((Hoja2!$A$2:$A$121&""=B31&"")*(TRIM(Hoja2!$F$2:$F$121)=TRIM(N31))*(Hoja2!$L$2:$L$121="")*Hoja2!$I$2:$I$121)))} | AJ31: CO05 LN-Cabecera Bucaramanga | AK31: CABECERA
D32: =IF(ISERROR(VLOOKUP(B32,$A$61:$C$30467,3,FALSE))=TRUE," ",VLOOKUP(B32,$A$61:$C$30467,3,FALSE)) | E32: =IF(ISERROR(VLOOKUP(B32,$A$61:$C$30000,2,FALSE))=TRUE," ",VLOOKUP(B32,$A$61:$C$30000,2,FALSE)) | AD32: Ibagye | AE32: CO14 LN-ALPOPULAR CUCUTA | AH32: {=IF(B32="","",IF(SUMPRODUCT((Hoja2!$A$2:$A$121&""=B32&"")*(TRIM(Hoja2!$F$2:$F$121)=TRIM(N32))*(TRIM(Hoja2!$L$2:$L$121)=TRIM(W32)))>0,SUMPRODUCT((Hoja2!$A$2:$A$121&""=B32&"")*(TRIM(Hoja2!$F$2:$F$121)=TRIM(N32))*(TRIM(Hoja2!$L$2:$L$121)=TRIM(W32))*Hoja2!$I$2:$I$121),SUMPRODUCT((Hoja2!$A$2:$A$121&""=B32&"")*(TRIM(Hoja2!$F$2:$F$121)=TRIM(N32))*(Hoja2!$L$2:$L$121="")*Hoja2!$I$2:$I$121)))} | AJ32: CO05 LN-Cabecera Bucaramanga | AK32: WOM
D33: =IF(ISERROR(VLOOKUP(B33,$A$61:$C$30467,3,FALSE))=TRUE," ",VLOOKUP(B33,$A$61:$C$30467,3,FALSE)) | E33: =IF(ISERROR(VLOOKUP(B33,$A$61:$C$30000,2,FALSE))=TRUE," ",VLOOKUP(B33,$A$61:$C$30000,2,FALSE)) | AD33: Villavicencio | AE33: CO15 LN Ibague Contratista | AH33: {=IF(B33="","",IF(SUMPRODUCT((Hoja2!$A$2:$A$121&""=B33&"")*(TRIM(Hoja2!$F$2:$F$121)=TRIM(N33))*(TRIM(Hoja2!$L$2:$L$121)=TRIM(W33)))>0,SUMPRODUCT((Hoja2!$A$2:$A$121&""=B33&"")*(TRIM(Hoja2!$F$2:$F$121)=TRIM(N33))*(TRIM(Hoja2!$L$2:$L$121)=TRIM(W33))*Hoja2!$I$2:$I$121),SUMPRODUCT((Hoja2!$A$2:$A$121&""=B33&"")*(TRIM(Hoja2!$F$2:$F$121)=TRIM(N33))*(Hoja2!$L$2:$L$121="")*Hoja2!$I$2:$I$121)))} | AJ33: CO06 LN-Almagrario Bucaramanga | AK33: ALMAGRARIO
D34: =IF(ISERROR(VLOOKUP(B34,$A$61:$C$30467,3,FALSE))=TRUE," ",VLOOKUP(B34,$A$61:$C$30467,3,FALSE)) | E34: =IF(ISERROR(VLOOKUP(B34,$A$61:$C$30000,2,FALSE))=TRUE," ",VLOOKUP(B34,$A$61:$C$30000,2,FALSE)) | AD34: Medellin | AE34: CO16 LN-Ibague | AH34: {=IF(B34="","",IF(SUMPRODUCT((Hoja2!$A$2:$A$121&""=B34&"")*(TRIM(Hoja2!$F$2:$F$121)=TRIM(N34))*(TRIM(Hoja2!$L$2:$L$121)=TRIM(W34)))>0,SUMPRODUCT((Hoja2!$A$2:$A$121&""=B34&"")*(TRIM(Hoja2!$F$2:$F$121)=TRIM(N34))*(TRIM(Hoja2!$L$2:$L$121)=TRIM(W34))*Hoja2!$I$2:$I$121),SUMPRODUCT((Hoja2!$A$2:$A$121&""=B34&"")*(TRIM(Hoja2!$F$2:$F$121)=TRIM(N34))*(Hoja2!$L$2:$L$121="")*Hoja2!$I$2:$I$121)))} | AJ34: CO07 LN-Piedecuesta Bucaramanga | AK34: PIEDECUESTA
D35: =IF(ISERROR(VLOOKUP(B35,$A$61:$C$30467,3,FALSE))=TRUE," ",VLOOKUP(B35,$A$61:$C$30467,3,FALSE)) | E35: =IF(ISERROR(VLOOKUP(B35,$A$61:$C$30000,2,FALSE))=TRUE," ",VLOOKUP(B35,$A$61:$C$30000,2,FALSE)) | Z35: {=_xlfn._xlws.FILTER(TablaOpciones[Opcion],TablaOpciones[Planta]=P21,0)} -> 0 | AA35: {=_xlfn._xlws.FILTER(TablaOpciones[Opcion],TablaOpciones[Planta]=M21,0)} -> ALMAGRARIO | AD35: Pasto | AE35: CO17 LN-Almagrario Medellin | AH35: {=IF(B35="","",IF(SUMPRODUCT((Hoja2!$A$2:$A$121&""=B35&"")*(TRIM(Hoja2!$F$2:$F$121)=TRIM(N35))*(TRIM(Hoja2!$L$2:$L$121)=TRIM(W35)))>0,SUMPRODUCT((Hoja2!$A$2:$A$121&""=B35&"")*(TRIM(Hoja2!$F$2:$F$121)=TRIM(N35))*(TRIM(Hoja2!$L$2:$L$121)=TRIM(W35))*Hoja2!$I$2:$I$121),SUMPRODUCT((Hoja2!$A$2:$A$121&""=B35&"")*(TRIM(Hoja2!$F$2:$F$121)=TRIM(N35))*(Hoja2!$L$2:$L$121="")*Hoja2!$I$2:$I$121)))} | AJ35: CO08 LN-Santa Monica Cali | AK35: Santa Monica
D36: =IF(ISERROR(VLOOKUP(B36,$A$61:$C$30467,3,FALSE))=TRUE," ",VLOOKUP(B36,$A$61:$C$30467,3,FALSE)) | E36: =IF(ISERROR(VLOOKUP(B36,$A$61:$C$30000,2,FALSE))=TRUE," ",VLOOKUP(B36,$A$61:$C$30000,2,FALSE)) | AA36: NODO | AE36: CO18 LN-Nodo Centro Medellin | AH36: {=IF(B36="","",IF(SUMPRODUCT((Hoja2!$A$2:$A$121&""=B36&"")*(TRIM(Hoja2!$F$2:$F$121)=TRIM(N36))*(TRIM(Hoja2!$L$2:$L$121)=TRIM(W36)))>0,SUMPRODUCT((Hoja2!$A$2:$A$121&""=B36&"")*(TRIM(Hoja2!$F$2:$F$121)=TRIM(N36))*(TRIM(Hoja2!$L$2:$L$121)=TRIM(W36))*Hoja2!$I$2:$I$121),SUMPRODUCT((Hoja2!$A$2:$A$121&""=B36&"")*(TRIM(Hoja2!$F$2:$F$121)=TRIM(N36))*(Hoja2!$L$2:$L$121="")*Hoja2!$I$2:$I$121)))} | AJ36: CO08 LN-Santa Monica Cali | AK36: WOM
D37: =IF(ISERROR(VLOOKUP(B37,$A$61:$C$30467,3,FALSE))=TRUE," ",VLOOKUP(B37,$A$61:$C$30467,3,FALSE)) | E37: =IF(ISERROR(VLOOKUP(B37,$A$61:$C$30000,2,FALSE))=TRUE," ",VLOOKUP(B37,$A$61:$C$30000,2,FALSE)) | AA37: WOM | AE37: CO19 LN-Almagrario Monteria | AH37: {=IF(B37="","",IF(SUMPRODUCT((Hoja2!$A$2:$A$121&""=B37&"")*(TRIM(Hoja2!$F$2:$F$121)=TRIM(N37))*(TRIM(Hoja2!$L$2:$L$121)=TRIM(W37)))>0,SUMPRODUCT((Hoja2!$A$2:$A$121&""=B37&"")*(TRIM(Hoja2!$F$2:$F$121)=TRIM(N37))*(TRIM(Hoja2!$L$2:$L$121)=TRIM(W37))*Hoja2!$I$2:$I$121),SUMPRODUCT((Hoja2!$A$2:$A$121&""=B37&"")*(TRIM(Hoja2!$F$2:$F$121)=TRIM(N37))*(Hoja2!$L$2:$L$121="")*Hoja2!$I$2:$I$121)))} | AJ37: CO09 LN-Almagrario Cali | AK37: ALMAGRARIO
D38: =IF(ISERROR(VLOOKUP(B38,$A$61:$C$30467,3,FALSE))=TRUE," ",VLOOKUP(B38,$A$61:$C$30467,3,FALSE)) | E38: =IF(ISERROR(VLOOKUP(B38,$A$61:$C$30000,2,FALSE))=TRUE," ",VLOOKUP(B38,$A$61:$C$30000,2,FALSE)) | AE38: CO20 LN-Nodo Castellana Monteria | AH38: {=IF(B38="","",IF(SUMPRODUCT((Hoja2!$A$2:$A$121&""=B38&"")*(TRIM(Hoja2!$F$2:$F$121)=TRIM(N38))*(TRIM(Hoja2!$L$2:$L$121)=TRIM(W38)))>0,SUMPRODUCT((Hoja2!$A$2:$A$121&""=B38&"")*(TRIM(Hoja2!$F$2:$F$121)=TRIM(N38))*(TRIM(Hoja2!$L$2:$L$121)=TRIM(W38))*Hoja2!$I$2:$I$121),SUMPRODUCT((Hoja2!$A$2:$A$121&""=B38&"")*(TRIM(Hoja2!$F$2:$F$121)=TRIM(N38))*(Hoja2!$L$2:$L$121="")*Hoja2!$I$2:$I$121)))} | AJ38: CO10 LN-Almaviva Cartagena | AK38: Almaviva
AE39: CO21 LN-Pasto | AJ39: CO11 LN-Bazurto Cartagena | AK39: BAZURTO
B40: OBSERVACIONES: | AE40: CO22 LN-Popayan | AJ40: CO11 LN-Bazurto Cartagena | AK40: WOM
AE41: CO23 LN-Nodo Centro Santa Marta | AJ41: CO12 LN-CFX Cartagena | AK41: CFX
AE42: CO24 LN-Deca Santa Marta | AJ42: CO13 LN-Cucuta | AK42: OFICINA
Z43: {=_xlfn._xlws.FILTER(TablaOpciones[Opcion],TablaOpciones[Planta]=P22,0)} -> 0 | AA43: {=_xlfn._xlws.FILTER(TablaOpciones[Opcion],TablaOpciones[Planta]=M22,0)} -> ALMAGRARIO | AE43: CO25 LN-Ocean Mall Santa Marta | AJ43: CO13 LN-Cucuta | AK43: WOM
AA44: NODO | AE44: CO26 LN-Sincelejo | AJ44: CO14 LN-ALPOPULAR CUCUTA | AK44: ALPOPULAR
B45: Solicitado por: | H45: Aprobado por: | AA45: WOM | AE45: CO27 LN-Ingenial Valledupar | AJ45: CO15 LN Ibague Contratista | AK45: BODEGA PE
B46: Fecha: | H46: Fecha: | AE46: CO28 LN-Nodo Centro Valledupar | AJ46: CO16 LN-Ibague | AK46: WOM
AE47: CO29 LN Villavicencio | AJ47: CO16 LN-Ibague | AK47: USADOS
AJ48: CO17 LN-Almagrario Medellin | AK48: ALMAGRARIO
B49: Liberty2025* | AJ49: CO18 LN-Nodo Centro Medellin | AK49: NODO CENTRO
AJ50: CO19 LN-Almagrario Monteria | AK50: ALMAGRARIO
AJ51: CO20 LN-Nodo Castellana Monteria | AK51: NODO CASTELLANA
Z52: {=_xlfn._xlws.FILTER(TablaOpciones[Opcion],TablaOpciones[Planta]=P23,0)} -> 0 | AA52: {=_xlfn._xlws.FILTER(TablaOpciones[Opcion],TablaOpciones[Planta]=M23,0)} -> ALMAGRARIO | AJ52: CO20 LN-Nodo Castellana Monteria | AK52: WOM
AA53: NODO | AJ53: CO21 LN-Pasto | AK53: BODEGA PASTO
AA54: WOM | AJ54: CO21 LN-Pasto | AK54: WOM
AJ55: CO22 LN-Popayan | AK55: CONTRATISTA
AJ56: CO22 LN-Popayan | AK56: WOM
AJ57: CO22 LN-Popayan | AK57: USADOS
AJ58: CO23 LN-Nodo Centro Santa Marta | AK58: NODO CENTRO
AJ59: CO24 LN-Deca Santa Marta | AK59: DECA
Z60: {=_xlfn._xlws.FILTER(TablaOpciones[Opcion],TablaOpciones[Planta]=P24,0)} -> 0 | AA60: {=_xlfn._xlws.FILTER(TablaOpciones[Opcion],TablaOpciones[Planta]=M24,0)} -> ALMAGRARIO | AJ60: CO25 LN-Ocean Mall Santa Marta | AK60: TAYRONA
A61: Número de artículo | B61: Descripción artículo | C61: Plan de U de M | J61: CO01 LN-BC Empresarial | N61: Dispos/Obsol/DOA | P61: CO01 | AA61: NODO | AJ61: CO25 LN-Ocean Mall Santa Marta | AK61: WOM
A62: 302451 | B62: Cisco Catalyst 9115AX Series | C62: EA | E62: -R | J62: CO02 LN-Steckerl | N62: PROMITEL | P62: CO01 | AA62: WOM | AJ62: CO26 LN-Sincelejo | AK62: NODO CENTRO
A63: 302452 | B63: Meraki MX68W Router | C63: EA | J63: CO03 LN-Bodega Nogales | N63: WOM | P63: CO01 | AJ63: CO26 LN-Sincelejo | AK63: WOM
A64: 302453 | B64: Catalyst 1300 16-port GE, PoE, 2x1G SFP | C64: EA | J64: CO04 LN-Bogota | N64: TRR | P64: CO01 | AJ64: CO27 LN-Ingenial Valledupar | AK64: INGENIAL
A65: 302462 | B65: Meraki MX68 Router | C65: EA | J65: CO05 LN-Cabecera Bucaramanga | N65: Dispos/Obsol/DOA | P65: CO02 | AJ65: CO28 LN-Nodo Centro Valledupar | AK65: NODO CENTRO
A66: 302543 | B66: EX2300 24-P 10/1 POE+ 4 X 1/10G SFP/ OPT | C66: EA | J66: CO06 LN-Almagrario Bucaramanga | N66: STECKERL | P66: CO02 | AJ66: CO28 LN-Nodo Centro Valledupar | AK66: WOM
A67: 302755 | B67: MERAKI AC PWR CORD F/ MX & MS US PLUG | C67: EA | J67: CO07 LN-Piedecuesta Bucaramanga | N67: TRR | P67: CO02 | AJ67: CO29 LN Villavicencio | AK67: ALMAGRARIO
A68: 302781 | B68: ASR 9000 4-PORT 100GE LINE CARD REF A9K- | C68: EA | J68: CO08 LN-Santa Monica Cali | N68: Dispos/Obsol/DOA | P68: CO04 | Z68: {=_xlfn._xlws.FILTER(TablaOpciones[Opcion],TablaOpciones[Planta]=P25,0)} -> 0 | AA68: {=_xlfn._xlws.FILTER(TablaOpciones[Opcion],TablaOpciones[Planta]=M25,0)} -> ALMAGRARIO | AJ68: CO29 LN Villavicencio | AK68: NODO
A69: 302786 | B69: MERAKI MS390 48GE L3 SWT REF MS39 | C69: EA | J69: CO09 LN-Almagrario Cali | N69: LN Bogota | P69: CO04 | AA69: NODO | AJ69: CO29 LN Villavicencio | AK69: WOM
A70: 302787 | B70: MERAKI MS390 8X10GE MOD REF MA-M | C70: EA | J70: CO10 LN-Almaviva Cartagena | N70: WOM | P70: CO04 | AA70: WOM | AJ70: 53 | AK70: SAL. MATERIAL DE CONSUMO
A71: 302790 | B71: MERAKI MS42 L3 CLD-16X 10G SFP+ SWIT MS | C71: EA | J71: CO11 LN-Bazurto Cartagena | N71: CN-COLBOG | P71: CO04 | AJ71: 54 | AK71: SAL. EQ. MAT. GARANTIAS
A72: 302791 | B72: MERAKI 40GBE QSFP CBL 05 METER REF MA-C | C72: EA | J72: CO12 LN-CFX Cartagena | N72: CN-PMBOG | P72: CO04 | AJ72: 55 | AK72: SAL. CARGO DIRECTO
A73: 302803 | B73: MERAKI 1000BASE SX MULTIMODE | C73: EA | J73: CO13 LN-Cucuta | N73: COLCSC NEW | P73: CO04 | AJ73: 56 | AK73: SALIDAS VARIAS
A74: 302804 | B74: MERAKI MS21 1G L2 CLD-48X GIGE 370W POE | C74: EA | J74: CO14 LN-ALPOPULAR CUCUTA | N74: CLCSC USED | P74: CO04 | AJ74: 57 | AK74: SAL. EQ. DE TELECOMUNICACION
A75: 302827 | B75: EX2300 24-P 10/1 POE+ 4 X 1/10G SFP/ OPT | C75: EA | J75: CO15 LN Ibague Contratista | N75: DATACENTER | P75: CO04 | AJ75: 58 | AK75: SAL. RACKS, GAB/TES, CANALETAS
A76: 302852 | B76: SFP+ 10G-SR OM3 300M OM4 400M STAN TEMP | C76: EA | J76: CO16 LN-Ibague | N76: CFX | P76: CO04 | Z76: {=_xlfn._xlws.FILTER(TablaOpciones[Opcion],TablaOpciones[Planta]=P26,0)} -> 0 | AA76: {=_xlfn._xlws.FILTER(TablaOpciones[Opcion],TablaOpciones[Planta]=M26,0)} -> ALMAGRARIO | AJ76: 59 | AK76: SAL. EQ. DE MEDICIÒN, INSTRUME
A77: 302946 | B77: FORTIAP 221E | C77: EA | J77: CO17 LN-Almagrario Medellin | N77: WOM | P77: CO04 | AA77: NODO | AJ77: 60 | AK77: SAL. EQ. RESPALDO ELECTRICO
A78: 302990 | B78: FORTIGATE-40F ROUTER REF FG-40F | C78: EA | J78: CO18 LN-Nodo Centro Medellin | N78: TRR | P78: CO04 | AA78: WOM | AJ78: 61 | AK78: SAL. REDES DE FIBRA BACKBONE
A79: 304110 | B79: ASR-9006 CHASSIS ASR-9006-SYS | C79: EA | J79: CO19 LN-Almagrario Monteria | N79: Dispos/Obsol/DOA | P79: CO03 | AJ79: 62 | AK79: SAL. REDES DE FIBRA ACCESOS
A80: 304111 | B80: SMAR 8X5XNBD CISCO ASR920 SERIES | C80: EA | J80: CO20 LN-Nodo Castellana Monteria | N80: BAJA ROTACION | P80: CO03 | AJ80: 63 | AK80: SAL. PROG. DE COMPUTADORES
A81: 304112 | B81: ASR9K DC PWR ENTRY MOD VERS 2 SPARE | C81: EA | J81: CO21 LN-Pasto | N81: TRR | P81: CO05 | AJ81: 64 | AK81: SAL. ENRUTADORES, SWITCH, ACC
A82: 304113 | B82: ASR-9010 CHASSIS ASR-9010-SYS | C82: EA | J82: CO22 LN-Popayan | N82: Dispos/Obsol/DOA | P82: CO05 | AJ82: 65 | AK82: SAL. ORGANIZACION RED SDH
A83: 304114 | B83: ASR-9010 FAN TRAY VERSION 2 | C83: EA | J83: CO23 LN-Nodo Centro Santa Marta | N83: CABECERA | P83: CO05 | AJ83: 66 | AK83: SAL. PROYECTO TERNERA CHAMBACU
A84: 304115 | B84: ASR 9000 ROUTE SWT PROC 880 F/PACKET TRA | C84: EA | J84: CO24 LN-Deca Santa Marta | N84: WOM | P84: CO05 | Z84: {=_xlfn._xlws.FILTER(TablaOpciones[Opcion],TablaOpciones[Planta]=P27,0)} -> 0 | AA84: {=_xlfn._xlws.FILTER(TablaOpciones[Opcion],TablaOpciones[Planta]=M27,0)} -> ALMAGRARIO | AJ84: 67 | AK84: SAL. AMPLIACION DE RED
A85: 304116 | B85: ASR 900 ROUTE SWT PROC 3 400G XL SCALE | C85: EA | J85: CO25 LN-Ocean Mall Santa Marta | N85: TRR | P85: CO06 | AA85: NODO | AJ85: 68 | AK85: SAL. REDES DE ACCESOS DSLAM
A86: 304117 | B86: ASR 900 ROUTE SWT PROC 3 400G XL SCALE | C86: EA | J86: CO26 LN-Sincelejo | N86: Dispos/Obsol/DOA | P86: CO06 | AA86: WOM | AJ86: 69 | AK86: SAL. PROYECTO ALKARAWI
A87: 304118 | B87: ASR 903 FAN TRAY FILTER A903-FAN-F | C87: EA | J87: CO27 LN-Ingenial Valledupar | N87: ALMAGRARIO | P87: CO06 | AJ87: 70 | AK87: SAL. PROYECTO IRUS
A88: 304128 | B88: RUCKUS R650 DUAL 802.11 WIRE ACCESS PNT | C88: EA | J88: CO28 LN-Nodo Centro Valledupar | N88: TRR | P88: CO07 | AJ88: 71 | AK88: SAL. PROYECTO GIRON
A89: 304130 | B89: RUCKUS T750 8021 OUTD WIRE ACCESS POINT | C89: EA | J89: CO29 LN Villavicencio | N89: Dispos/Obsol/DOA | P89: CO07 | AJ89: 72 | AK89: SAL. EQUIPOS Y HERRTS A CARGO
A90: 304167 | B90: SRX380 SERV GATE INC HARD 16GEPOE+4X10GE | C90: EA | N90: PIEDECUESTA | P90: CO07 | AJ90: 81 | AK90: SAL. LEASING EQ. TEL, MED, RES
A91: 304215 | B91: FORTIGATE-80F | C91: EA | N91: TRR | P91: CO08 | AJ91: 82 | AK91: SAL. LEASING REDES BACKBONE
A92: 304273 | B92: RUCKUS R750 DUAL 802.11 WIRE ACCESS PNT | C92: EA | N92: Dispos/Obsol/DOA | P92: CO08 | Z92: {=_xlfn._xlws.FILTER(TablaOpciones[Opcion],TablaOpciones[Planta]=P28,0)} -> 0 | AA92: {=_xlfn._xlws.FILTER(TablaOpciones[Opcion],TablaOpciones[Planta]=M28,0)} -> ALMAGRARIO | AJ92: 83 | AK92: SAL. LEASING REDES ACCESOS
A93: 304371 | B93: ODF 48 P SC LSC1U-072-12 OFS | C93: EA | N93: Santa Monica | P93: CO08 | AA93: NODO | AJ93: 84 | AK93: SAL. LEASING AMPLIACION DE RED
A94: 304372 | B94: HERR RETENCION FIBRA DE 96 HILOS ADSS | C94: EA | N94: WOM | P94: CO08 | AA94: WOM
A95: 304373 | B95: SAR-AX W/ 12P ENET & GNSS -48/ VDC 3HE1 | C95: EA | N95: TRR | P95: CO09
A96: 304374 | B96: 7250 -IXR-E BIG 24X1 | C96: EA | N96: Dispos/Obsol/DOA | P96: CO09
A97: 304375 | B97: PS – 7250 IXR-E DC 3HE14785AA | C97: EA | N97: ALMAGRARIO | P97: CO09
A98: 304376 | B98: 7250 IXR-E RACK MNT BRAC TEN PACK | C98: EA | N98: TRR | P98: CO10
A99: 304377 | B99: 7250 -IXR-E BIG 14X1 | C99: EA | N99: Dispos/Obsol/DOA | P99: CO10
A100: 304378 | B100: AT PERF ELEM 4XRJ45 & 4X1G SFP PORT HARD | C100: EA | N100: Almaviva | P100: CO10 | Z100: {=_xlfn._xlws.FILTER(TablaOpciones[Opcion],TablaOpciones[Planta]=P29,0)} -> 0 | AA100: {=_xlfn._xlws.FILTER(TablaOpciones[Opcion],TablaOpciones[Planta]=M29,0)} -> 0
A101: 304379 | B101: DC A/B PWR CONN TERM BLOCK ADAP | C101: EA | N101: TRR | P101: CO11
A102: 304380 | B102: AT PERF ELEM 4XRJ45 & 4X1G SFP PORT HARD | C102: EA | N102: Dispos/Obsol/DOA | P102: CO11
A103: 304381 | B103: AC/DC PWR CORD NORTH AMER -C5 TERM | C103: EA | N103: BAZURTO | P103: CO11
A104: 304382 | B104: OP-M TRANSC 125G SM SINGLE FIB 1310 20KM | C104: EA | N104: WOM | P104: CO11
A105: 304383 | B105: OP-M SFP TRANSC 125G SM SINGLE FIB 1550 | C105: EA | N105: TRR | P105: CO12
A106: 304384 | B106: FIBRA 24 H ARMADA MONOM | C106: M | N106: Dispos/Obsol/DOA | P106: CO12
A107: 304385 | B107: CIERRE DE EMPA FOSC BOV-TM COMM | C107: EA | N107: CFX | P107: CO12
A108: 304386 | B108: HERRAJE RETENCION PLP 5.1-5.3 MM | C108: EA | N108: TRR | P108: CO13 | Z108: {=_xlfn._xlws.FILTER(TablaOpciones[Opcion],TablaOpciones[Planta]=P30,0)} -> 0 | AA108: {=_xlfn._xlws.FILTER(TablaOpciones[Opcion],TablaOpciones[Planta]=M30,0)} -> 0
A109: 304387 | B109: RETE 4090 SISX ACERO 90 -99MM SPAN 100 | C109: EA | N109: Dispos/Obsol/DOA | P109: CO13
A110: 304388 | B110: RETE 4090 SISC ACERO 100 -109MM SPAN 10 | C110: EA | N110: OFICINA | P110: CO13
...

Sheet Hoja2
A1: Material | B1: Material Description | C1: Plant | D1: Plant Name | E1: Storage Location | F1: Description of Storage Location | G1: Special Stock Type | H1: Special Stock Type Description | I1: Unrestricted Stock | J1: Stock in Quality Inspection | K1: Blocked Stock | L1: WBS Element
A2: 800376-R | B2: ME3600X/ME3800X DC PWR SUPPLY | C2: CO29 | D2: LN Villavicencio | E2: 0141 | F2: NODO | I2: 2 | J2: 0 | K2: 0 | L2: ZZ.CO11.250130.31
A3: 525397-R | B3: GENCOM NETW / GLC-/ CISCO COMP SFP 100B | C3: CO29 | D3: LN Villavicencio | E3: 0141 | F3: NODO | I3: 3 | J3: 0 | K3: 0 | L3: ZZ.CO11.250130.31
A4: 524164-R | B4: PIGTAL SC/UPC SIMPLEX 1M | C4: CO29 | D4: LN Villavicencio | E4: 0141 | F4: NODO | I4: 13 | J4: 0 | K4: 0 | L4: ZZ.CO11.250130.31
A5: 523600-R | B5: PATCHCORD SC/UPC-SC/UPC 3M SPLX YLLW | C5: CO29 | D5: LN Villavicencio | E5: 0141 | F5: NODO | I5: 2 | J5: 0 | K5: 0 | L5: ZZ.CO11.250130.31
A6: 523272-R | B6: MARQ ELAB EN ACRI POLI CALI 20ES EN SCRE | C6: CO29 | D6: LN Villavicencio | E6: 0141 | F6: NODO | I6: 470 | J6: 0 | K6: 0 | L6: ZZ.CO11.250130.31
A7: 523270-R | B7: MARQ PLAS CBL PMASE PREI | C7: CO29 | D7: LN Villavicencio | E7: 0141 | F7: NODO | I7: 2 | J7: 0 | K7: 0 | L7: ZZ.CO11.250130.31
A8: 523098-R | B8: HERRAJE R 117-128 MM NACIONAL | C8: CO29 | D8: LN Villavicencio | E8: 0140 | F8: ALMAGRARIO | I8: 13 | J8: 0 | K8: 0 | L8: ZZ.CO11.250130.31
A9: 523098-R | B9: HERRAJE R 117-128 MM NACIONAL | C9: CO29 | D9: LN Villavicencio | E9: 0141 | F9: NODO | I9: 44 | J9: 0 | K9: 0 | L9: ZZ.CO11.250130.31
A10: 523042-R | B10: PIGTAIL SC MONOM 3 MTS | C10: CO29 | D10: LN Villavicencio | E10: 0141 | F10: NODO | I10: 1 | J10: 0 | K10: 0 | L10: ZZ.CO11.250130.31
A11: 523040-R | B11: PIGTAIL SC 15 MTS MONOMODO | C11: CO29 | D11: LN Villavicencio | E11: 0141 | F11: NODO | I11: 18 | J11: 0 | K11: 0 | L11: ZZ.CO11.250130.31
A12: 522897-R | B12: CAJA TERMINAL CONECTOR SC/UPC 4-6 HILOS | C12: CO29 | D12: LN Villavicencio | E12: 0141 | F12: NODO | I12: 3 | J12: 0 | K12: 0 | L12: ZZ.CO11.250130.31
A13: 522662-R | B13: CIERRE HERMETICO TYCO 192H | C13: CO29 | D13: LN Villavicencio | E13: 0140 | F13: ALMAGRARIO | I13: 1 | J13: 0 | K13: 0 | L13: ZZ.CO11.250130.31
... A35: 800296 | B35: SFP TRANSC 155M SM SF 1490T/1310R 20K LC | C35: CO29 | D35: LN Villavicencio | E35: 0141 | F35: NODO | I35: 2 | J35: 0 | K35: 0 | L35: ZZ.CO11.250130.31
A36: 800295 | B36: SFP TRANSC 155M SM SF 1310T/1490R 20K LC | C36: CO29 | D36: LN Villavicencio | E36: 0141 | F36: NODO | G36: Q | H36: Project Stock | I36: 3 | J36: 0 | K36: 0 | L36: ZZ.CO11.250212.08
A37: 523272 | B37: MARQ ELAB EN ACRI POLI CALI 20ES EN SCRE | C37: CO29 | D37: LN Villavicencio | E37: 0140 | F37: ALMAGRARIO | I37: 10 | J37: 0 | K37: 0 | L37: ZZ.CO11.250130.31
A38: 523272 | B38: MARQ ELAB EN ACRI POLI CALI 20ES EN SCRE | C38: CO29 | D38: LN Villavicencio | E38: 0141 | F38: NODO | I38: 61 | J38: 0 | K38: 0 | L38: ZZ.CO11.250130.31
A39: 523270 | B39: MARQ PLAS CBL PMASE PREI | C39: CO29 | D39: LN Villavicencio | E39: 0140 | F39: ALMAGRARIO | I39: 5 | J39: 0 | K39: 0 | L39: ZZ.CO11.250130.31
A40: 523120 | B40: ARGOLLA POSTE PARA HERRAJES GPON | C40: CO29 | D40: LN Villavicencio | E40: 0140 | F40: ALMAGRARIO | I40: 270 | J40: 0 | K40: 0 | L40: ZZ.CO11.250130.31
A41: 523119 | B41: HERRAJE DE RETENCION FIBRA PLANA SISCOAX | C41: CO29 | D41: LN Villavicencio | E41: 0140 | F41: ALMAGRARIO | I41: 244 | J41: 0 | K41: 0 | L41: ZZ.CO11.250130.31
A42: 523102 | B42: HERR S FO 12-48 ADSS 90 -110 MM NACI | C42: CO29 | D42: LN Villavicencio | E42: 0141 | F42: NODO | G42: Q | H42: Project Stock | I42: 42 | J42: 0 | K42: 0 | L42: ZZ.CO11.260017.08
A43: 523098 | B43: HERRAJE R 117-128 MM NACIONAL | C43: CO29 | D43: LN Villavicencio | E43: 0141 | F43: NODO | G43: Q | H43: Project Stock | I43: 76 | J43: 0 | K43: 0 | L43: ZZ.CO11.260017.08
A44: 523098 | B44: HERRAJE R 117-128 MM NACIONAL | C44: CO29 | D44: LN Villavicencio | E44: 0141 | F44: NODO | G44: Q | H44: Project Stock | I44: 45 | J44: 0 | K44: 0 | L44: ZZ.CO11.260193.08
A45: 523042 | B45: PIGTAIL SC MONOM 3 MTS | C45: CO29 | D45: LN Villavicencio | E45: 0141 | F45: NODO | I45: 14 | J45: 0 | K45: 0 | L45: ZZ.CO11.250130.31
A46: 523024 | B46: PATCHCORD LC-SC SM 8 MTS DUPLEX | C46: CO29 | D46: LN Villavicencio | E46: 0141 | F46: NODO | I46: 3 | J46: 0 | K46: 0 | L46: ZZ.CO11.250130.31
A47: 523024 | B47: PATCHCORD LC-SC SM 8 MTS DUPLEX | C47: CO29 | D47: LN Villavicencio | E47: 0141 | F47: NODO | G47: Q | H47: Project Stock | I47: 9 | J47: 0 | K47: 0 | L47: ZZ.CO11.260126.31
A48: 523023 | B48: PATCHCORD LC-SC SM 6 MTS DUPLEX | C48: CO29 | D48: LN Villavicencio | E48: 0141 | F48: NODO | G48: Q | H48: Project Stock | I48: 10 | J48: 0 | K48: 0 | L48: ZZ.CO11.260126.31
A49: 523022 | B49: PATCHCORD LC-SC SM 2 MTS DUPLEX | C49: CO29 | D49: LN Villavicencio | E49: 0141 | F49: NODO | G49: Q | H49: Project Stock | I49: 10 | J49: 0 | K49: 0 | L49: ZZ.CO11.260126.31
A50: 523019 | B50: PATCHCORD LC-SC SM 1.5 MTS DUPLEX | C50: CO29 | D50: LN Villavicencio | E50: 0141 | F50: NODO | G50: Q | H50: Project Stock | I50: 8 | J50: 0 | K50: 0 | L50: ZZ.CO11.260126.31
A51: 523017 | B51: PATCHCORD LC-SC SM 5 MTS DUPLEX | C51: CO29 | D51: LN Villavicencio | E51: 0141 | F51: NODO | G51: Q | H51: Project Stock | I51: 10 | J51: 0 | K51: 0 | L51: ZZ.CO11.260126.31
A52: 522969 | B52: PATCHCORD LC-LC SM 10 MTS DUPLEX | C52: CO29 | D52: LN Villavicencio | E52: 0141 | F52: NODO | I52: 5 | J52: 0 | K52: 0 | L52: ZZ.CO11.250130.31
A53: 522966 | B53: PATCHCORD LC-LC SM 8 MTS DUPLEX | C53: CO29 | D53: LN Villavicencio | E53: 0141 | F53: NODO | I53: 5 | J53: 0 | K53: 0 | L53: ZZ.CO11.250130.31
A54: 522965 | B54: PATCHCORD LC-LC SM 5 MTS DUPLEX | C54: CO29 | D54: LN Villavicencio | E54: 0141 | F54: NODO | G54: Q | H54: Project Stock | I54: 5 | J54: 0 | K54: 0 | L54: ZZ.CO11.260126.31
A55: 522963 | B55: PATCHCORD LC-LC SM 3 MTS DUPLEX | C55: CO29 | D55: LN Villavicencio | E55: 0141 | F55: NODO | G55: Q | H55: Project Stock | I55: 5 | J55: 0 | K55: 0 | L55: ZZ.CO11.260126.31
A56: 522962 | B56: PATCHCORD LC-SC SM 3 MTS DUPLEX | C56: CO29 | D56: LN Villavicencio | E56: 0141 | F56: NODO | G56: Q | H56: Project Stock | I56: 10 | J56: 0 | K56: 0 | L56: ZZ.CO11.260126.31
A57: 522958 | B57: PATCHCORD LC-LC SM 1.5 MTS DUPLEX | C57: CO29 | D57: LN Villavicencio | E57: 0141 | F57: NODO | G57: Q | H57: Project Stock | I57: 5 | J57: 0 | K57: 0 | L57: ZZ.CO11.260126.31
A58: 522948 | B58: PATCHCORD SC-SC SM 1.5 MTS DUPLEX | C58: CO29 | D58: LN Villavicencio | E58: 0141 | F58: NODO | G58: Q | H58: Project Stock | I58: 5 | J58: 0 | K58: 0 | L58: ZZ.CO11.260126.31
A59: 522934 | B59: TUBO TERMOCONTRACTIL 45MM | C59: CO29 | D59: LN Villavicencio | E59: 0140 | F59: ALMAGRARIO | I59: 100 | J59: 0 | K59: 0 | L59: ZZ.CO11.250130.31
A60: 522934 | B60: TUBO TERMOCONTRACTIL 45MM | C60: CO29 | D60: LN Villavicencio | E60: 0141 | F60: NODO | I60: 300 | J60: 0 | K60: 0 | L60: ZZ.CO11.250130.31
A61: 522934 | B61: TUBO TERMOCONTRACTIL 45MM | C61: CO29 | D61: LN Villavicencio | E61: 0141 | F61: NODO | G61: Q | H61: Project Stock | I61: 100 | J61: 0 | K61: 0 | L61: ZZ.CO11.260164.31
A62: 522933 | B62: TUBO TERMOCONTRACTIL 60 MM | C62: CO29 | D62: LN Villavicencio | E62: 0140 | F62: ALMAGRARIO | I62: 100 | J62: 0 | K62: 0 | L62: ZZ.CO11.250130.31
A63: 522933 | B63: TUBO TERMOCONTRACTIL 60 MM | C63: CO29 | D63: LN Villavicencio | E63: 0141 | F63: NODO | I63: 100 | J63: 0 | K63: 0 | L63: ZZ.CO11.250130.31
A64: 522933 | B64: TUBO TERMOCONTRACTIL 60 MM | C64: CO29 | D64: LN Villavicencio | E64: 0141 | F64: NODO | G64: Q | H64: Project Stock | I64: 100 | J64: 0 | K64: 0 | L64: ZZ.CO11.250212.08
A65: 522897 | B65: CAJA TERMINAL CONECTOR SC/UPC 4-6 HILOS | C65: CO29 | D65: LN Villavicencio | E65: 0141 | F65: NODO | G65: Q | H65: Project Stock | I65: 3 | J65: 0 | K65: 0 | L65: ZZ.CO11.260017.08
A66: 522897 | B66: CAJA TERMINAL CONECTOR SC/UPC 4-6 HILOS | C66: CO29 | D66: LN Villavicencio | E66: 0141 | F66: NODO | G66: Q | H66: Project Stock | I66: 7 | J66: 0 | K66: 0 | L66: ZZ.CO11.260126.31
A67: 522687 | B67: KIT REEN BASICO SELLO REDO RAYC | C67: CO29 | D67: LN Villavicencio | E67: 0141 | F67: NODO | G67: Q | H67: Project Stock | I67: 4 | J67: 0 | K67: 0 | L67: ZZ.CO11.250212.08
A68: 522686 | B68: KIT ODF ALTA DENS CON CAPA HASTA 24-48 | C68: CO29 | D68: LN Villavicencio | E68: 0140 | F68: ALMAGRARIO | I68: 2 | J68: 0 | K68: 0 | L68: ZZ.CO11.250130.31
A69: 522684 | B69: CIERRE 12H SILVER | C69: CO29 | D69: LN Villavicencio | E69: 0141 | F69: NODO | G69: Q | H69: Project Stock | I69: 5 | J69: 0 | K69: 0 | L69: ZZ.CO11.260017.08
A70: 522682 | B70: CIERRE DE EMPA KIT DOMO TIPO B4 REF CFED | C70: CO29 | D70: LN Villavicencio | E70: 0141 | F70: NODO | G70: Q | H70: Project Stock | I70: 2 | J70: 0 | K70: 0 | L70: ZZ.CO11.260051.06
A71: 522668 | B71: CIERRE HERMETICO 6-48 A8 FUS RAYCHEM | C71: CO29 | D71: LN Villavicencio | E71: 0141 | F71: NODO | G71: Q | H71: Project Stock | I71: 1 | J71: 0 | K71: 0 | L71: ZZ.CO11.250212.08
A72: 522668 | B72: CIERRE HERMETICO 6-48 A8 FUS RAYCHEM | C72: CO29 | D72: LN Villavicencio | E72: 0141 | F72: NODO | G72: Q | H72: Project Stock | I72: 3 | J72: 0 | K72: 0 | L72: ZZ.CO11.260126.31
A73: 522662 | B73: CIERRE HERMETICO TYCO 192H | C73: CO29 | D73: LN Villavicencio | E73: 0140 | F73: ALMAGRARIO | I73: 1 | J73: 0 | K73: 0 | L73: ZZ.CO11.250130.31
A74: 522653 | B74: CONV DE MEDIOS REFE REF MC-1 | C74: CO29 | D74: LN Villavicencio | E74: 0140 | F74: ALMAGRARIO | I74: 7 | J74: 0 | K74: 0 | L74: ZZ.CO11.250130.31
A75: 522653 | B75: CONV DE MEDIOS REFE REF MC-1 | C75: CO29 | D75: LN Villavicencio | E75: 0141 | F75: NODO | I75: 5 | J75: 0 | K75: 0 | L75: ZZ.CO11.250130.31
A76: 522653 | B76: CONV DE MEDIOS REFE REF MC-1 | C76: CO29 | D76: LN Villavicencio | E76: 0141 | F76: NODO | G76: Q | H76: Project Stock | I76: 6 | J76: 0 | K76: 0 | L76: ZZ.CO11.260017.08
A77: 522643 | B77: 10/1 RJ-45 100 MT TO 100/ SFP SLOT | C77: CO29 | D77: LN Villavicencio | E77: 0140 | F77: ALMAGRARIO | I77: 3 | J77: 0 | K77: 0 | L77: ZZ.CO11.250130.31
A78: 522643 | B78: 10/1 RJ-45 100 MT TO 100/ SFP SLOT | C78: CO29 | D78: LN Villavicencio | E78: 0141 | F78: NODO | I78: 1 | J78: 0 | K78: 0 | L78: ZZ.CO11.250130.31
A79: 522643 | B79: 10/1 RJ-45 100 MT TO 100/ SFP SLOT | C79: CO29 | D79: LN Villavicencio | E79: 0141 | F79: NODO | G79: Q | H79: Project Stock | I79: 4 | J79: 0 | K79: 0 | L79: ZZ.CO11.250212.08
A80: 522407 | B80: SFP+ TRNSC 10G SM DL FIB 1310NM 10 KM LC | C80: CO29 | D80: LN Villavicencio | E80: 0141 | F80: NODO | I80: 1 | J80: 0 | K80: 0 | L80: ZZ.CO11.250130.31
A81: 522318 | B81: 7210 SAS-M FAN ABANICO | C81: CO29 | D81: LN Villavicencio | E81: 0140 | F81: ALMAGRARIO | I81: 2 | J81: 0 | K81: 0 | L81: ZZ.CO11.250130.31
A82: 522315 | B82: 7210 SAS-M 24F -48V DC | C82: CO29 | D82: LN Villavicencio | E82: 0140 | F82: ALMAGRARIO | I82: 1 | J82: 0 | K82: 0 | L82: ZZ.CO11.250130.31
A83: 522306 | B83: PWR SUP 7210 SAS-M DC | C83: CO29 | D83: LN Villavicencio | E83: 0140 | F83: ALMAGRARIO | I83: 1 | J83: 0 | K83: 0 | L83: ZZ.CO11.250130.31
A84: 522171 | B84: FIBRA 4 H USO INTERIOR MONOM | C84: CO29 | D84: LN Villavicencio | E84: 0140 | F84: ALMAGRARIO | G84: Q | H84: Project Stock | I84: 487 | J84: 0 | K84: 0 | L84: ZZ.CO11.250212.08
A85: 522171 | B85: FIBRA 4 H USO INTERIOR MONOM | C85: CO29 | D85: LN Villavicencio | E85: 0141 | F85: NODO | G85: Q | H85: Project Stock | I85: 4000 | J85: 0 | K85: 0 | L85: ZZ.CO11.260126.31
A86: 522167 | B86: FIBRA 96 H ADSS MONOM | C86: CO29 | D86: LN Villavicencio | E86: 0140 | F86: ALMAGRARIO | I86: 78 | J86: 0 | K86: 0 | L86: ZZ.CO11.250130.31
A87: 522157 | B87: FIBRA 48 H ADSS MONOM | C87: CO29 | D87: LN Villavicencio | E87: 0140 | F87: ALMAGRARIO | I87: 600 | J87: 0 | K87: 0 | L87: ZZ.CO11.250130.31
A88: 522157 | B88: FIBRA 48 H ADSS MONOM | C88: CO29 | D88: LN Villavicencio | E88: 0140 | F88: ALMAGRARIO | G88: Q | H88: Project Stock | I88: 3000 | J88: 0 | K88: 0 | L88: ZZ.CO11.260039.08
A89: 522155 | B89: FIBRA 12 H ADSS TTH MONOM | C89: CO29 | D89: LN Villavicencio | E89: 0140 | F89: ALMAGRARIO | G89: Q | H89: Project Stock | I89: 2804 | J89: 0 | K89: 0 | L89: ZZ.CO11.260126.31
A90: 522109 | B90: FOSC HIGH CAPA TRAYS 24 SPLI PER TRAY | C90: CO29 | D90: LN Villavicencio | E90: 0140 | F90: ALMAGRARIO | I90: 2 | J90: 0 | K90: 0 | L90: ZZ.CO11.250130.31
A91: 522109 | B91: FOSC HIGH CAPA TRAYS 24 SPLI PER TRAY | C91: CO29 | D91: LN Villavicencio | E91: 0141 | F91: NODO | G91: Q | H91: Project Stock | I91: 4 | J91: 0 | K91: 0 | L91: ZZ.CO11.260126.31
A92: 521930 | B92: PATCHCORD FC-SC SM 5 MTS DUPLEX | C92: CO29 | D92: LN Villavicencio | E92: 0141 | F92: NODO | I92: 2 | J92: 0 | K92: 0 | L92: ZZ.CO11.250130.31
A93: 521926 | B93: PATCHCORD SC-SC SM 5 MTS DUPLEX | C93: CO29 | D93: LN Villavicencio | E93: 0141 | F93: NODO | G93: Q | H93: Project Stock | I93: 2 | J93: 0 | K93: 0 | L93: ZZ.CO11.260126.31
A94: 521925 | B94: PATCHCORD SC-SC SM 3 MTS DUPLEX | C94: CO29 | D94: LN Villavicencio | E94: 0141 | F94: NODO | G94: Q | H94: Project Stock | I94: 5 | J94: 0 | K94: 0 | L94: ZZ.CO11.260126.31
A95: 521919 | B95: ODF 48 P SC LSC1U-072-12 OFS | C95: CO29 | D95: LN Villavicencio | E95: 0140 | F95: ALMAGRARIO | I95: 1 | J95: 0 | K95: 0 | L95: ZZ.CO11.250130.31
A96: 304373 | B96: SAR-AX W/ 12P ENET & GNSS -48/ VDC 3HE1 | C96: CO29 | D96: LN Villavicencio | E96: 0142 | F96: WOM | I96: 1 | J96: 0 | K96: 0 | L96: ZZ.CO11.250130.31

Sheet Hoja1
B3: 302755-R | C3: MERAKI AC PWR CORD F/ MX & MS US PLUG | D3: EA
B4: 302781-R | C4: ASR 9000 4-PORT 100GE LINE CARD REF A9K- | D4: EA
B5: 302786-R | C5: MERAKI MS390 48GE L3 SWT REF MS39 | D5: EA
B6: 302787-R | C6: MERAKI MS390 8X10GE MOD REF MA-M | D6: EA
B7: 302790-R | C7: MERAKI MS42 L3 CLD-16X 10G SFP+ SWIT MS | D7: EA
B8: 302791-R | C8: MERAKI 40GBE QSFP CBL 05 METER REF MA-C | D8: EA
B9: 302803-R | C9: MERAKI 1000BASE SX MULTIMODE | D9: EA
B10: 302804-R | C10: MERAKI MS21 1G L2 CLD-48X GIGE 370W POE | D10: EA
B11: 302852-R | C11: SFP+ 10G-SR OM3 300M OM4 400M STAN TEMP | D11: EA
B12: 302946-R | C12: FORTIAP 221E | D12: EA
B13: 302990-R | C13: FORTIGATE-40F ROUTER REF FG-40F | D13: EA
B14: 304110-R | C14: ASR-9006 CHASSIS ASR-9006-SYS | D14: EA
... B1915: 801761-R | C1915: GABI ALMA DE CABLES OSP- IFC | D1915: EA
